google_workspace_group_manager/__init__.py
google_workspace_group_manager/config.py
google_workspace_group_manager/group_manager.py
tests/__init__.py
tests/test_group_manager.py
Google_Group_Admin_API-1.0.0.dist-info/LICENSE
Google_Group_Admin_API-1.0.0.dist-info/METADATA
Google_Group_Admin_API-1.0.0.dist-info/WHEEL
Google_Group_Admin_API-1.0.0.dist-info/top_level.txt
Google_Group_Admin_API-1.0.0.dist-info/RECORD
