Metadata-Version: 2.1
Name: Google-Group-Admin-API
Version: 1.0.0
Summary: A Python library for managing Google Cloud Platform groups via Google Workspace Directory API
Home-page: https://github.com/martialo12/Google-Group-Admin-API
Author: Wafo Martial Hermann
Author-email: martialo218@gmail.com
Classifier: Development Status :: 5 - Production/Stable
Classifier: Intended Audience :: Developers
Classifier: License :: OSI Approved :: MIT License
Classifier: Programming Language :: Python :: 3
Classifier: Programming Language :: Python :: 3.6
Classifier: Programming Language :: Python :: 3.7
Classifier: Programming Language :: Python :: 3.8
Classifier: Programming Language :: Python :: 3.9
Classifier: Programming Language :: Python :: 3.10
Classifier: Operating System :: OS Independent
Requires-Python: >=3.6
License-File: LICENSE
Requires-Dist: google-auth ==2.6.6
Requires-Dist: google-api-python-client ==2.41.0
